wyrdbound_dice/__init__.py
wyrdbound_dice/debug_logger.py
wyrdbound_dice/dice.py
wyrdbound_dice/errors.py
wyrdbound_dice/expression_lexer.py
wyrdbound_dice/expression_parser.py
wyrdbound_dice/expression_token.py
wyrdbound_dice/roll_result.py
wyrdbound_dice-0.0.2.dist-info/licenses/LICENSE
wyrdbound_dice-0.0.2.dist-info/METADATA
wyrdbound_dice-0.0.2.dist-info/WHEEL
wyrdbound_dice-0.0.2.dist-info/top_level.txt
wyrdbound_dice-0.0.2.dist-info/RECORD
