Metadata-Version: 2.4
Name: wyrdbound-dice
Version: 0.0.2
Summary: A comprehensive dice rolling library for tabletop RPGs
Author-email: The Wyrd One <wyrdbound@proton.me>
Maintainer-email: The Wyrd One <wyrdbound@proton.me>
License: MIT
Project-URL: Homepage, https://github.com/wyrdbound/wyrdbound-dice
Project-URL: Repository, https://github.com/wyrdbound/wyrdbound-dice
Project-URL: Documentation, https://github.com/wyrdbound/wyrdbound-dice#readme
Project-URL: Bug Tracker, https://github.com/wyrdbound/wyrdbound-dice/issues
Keywords: dice,tabletop,rpg,ttrpg,gaming,random,probability
Classifier: Development Status :: 5 - Production/Stable
Classifier: Intended Audience :: Developers
Classifier: Intended Audience :: End Users/Desktop
Classifier: License :: OSI Approved :: MIT License
Classifier: Operating System :: OS Independent
Classifier: Programming Language :: Python :: 3
Classifier: Programming Language :: Python :: 3.8
Classifier: Programming Language :: Python :: 3.9
Classifier: Programming Language :: Python :: 3.10
Classifier: Programming Language :: Python :: 3.11
Classifier: Programming Language :: Python :: 3.12
Classifier: Topic :: Games/Entertainment :: Role-Playing
Classifier: Topic :: Software Development :: Libraries :: Python Modules
Classifier: Topic :: Scientific/Engineering :: Mathematics
Requires-Python: >=3.8
License-File: LICENSE
Provides-Extra: visualization
Requires-Dist: matplotlib>=3.7.0; extra == "visualization"
Provides-Extra: dev
Requires-Dist: pytest>=7.0.0; extra == "dev"
Requires-Dist: pytest-cov>=4.0.0; extra == "dev"
Requires-Dist: black>=23.0.0; extra == "dev"
Requires-Dist: isort>=5.12.0; extra == "dev"
Requires-Dist: ruff>=0.1.0; extra == "dev"
Dynamic: license-file
